autoregistry/__init__.py
autoregistry/_registry.py
autoregistry/_version.py
autoregistry/config.py
autoregistry/exceptions.py
autoregistry/py.typed
autoregistry/pydantic.py
autoregistry/regex.py
autoregistry-1.2.1.dist-info/METADATA
autoregistry-1.2.1.dist-info/WHEEL
autoregistry-1.2.1.dist-info/licenses/LICENSE
autoregistry-1.2.1.dist-info/RECORD
