Metadata-Version: 2.4
Name: autoregistry
Version: 1.2.1
Summary: Automatic registry design-pattern for mapping names to functionality.
Project-URL: Homepage, https://github.com/BrianPugh/autoregistry
Project-URL: Repository, https://github.com/BrianPugh/autoregistry
Author: Brian Pugh
License-Expression: Apache-2.0
License-File: LICENSE
Classifier: Development Status :: 5 - Production/Stable
Classifier: Intended Audience :: Developers
Classifier: License :: OSI Approved :: Apache Software License
Classifier: Operating System :: OS Independent
Classifier: Programming Language :: Python :: 3
Classifier: Programming Language :: Python :: 3.8
Classifier: Programming Language :: Python :: 3.9
Classifier: Programming Language :: Python :: 3.10
Classifier: Programming Language :: Python :: 3.11
Classifier: Programming Language :: Python :: 3.12
Classifier: Programming Language :: Python :: 3.13
Classifier: Topic :: Software Development :: Libraries :: Python Modules
Classifier: Typing :: Typed
Requires-Python: >=3.8
Provides-Extra: docs
Requires-Dist: sphinx-copybutton>=0.5.0; extra == 'docs'
Requires-Dist: sphinx-rtd-theme<3.1,>=1.0; extra == 'docs'
Requires-Dist: sphinx<7.2,>=4.5; extra == 'docs'
Provides-Extra: pydantic
Requires-Dist: pydantic>=2.0; extra == 'pydantic'
